reco_utils/__init__.py
reco_utils/azureml/__init__.py
reco_utils/azureml/aks_utils.py
reco_utils/azureml/azureml_utils.py
reco_utils/azureml/svd_training.py
reco_utils/azureml/wide_deep_training.py
reco_utils/common/__init__.py
reco_utils/common/constants.py
reco_utils/common/general_utils.py
reco_utils/common/gpu_utils.py
reco_utils/common/notebook_memory_management.py
reco_utils/common/notebook_utils.py
reco_utils/common/plot.py
reco_utils/common/python_utils.py
reco_utils/common/spark_utils.py
reco_utils/common/tf_utils.py
reco_utils/common/timer.py
reco_utils/dataset/__init__.py
reco_utils/dataset/amazon_reviews.py
reco_utils/dataset/blob_utils.py
reco_utils/dataset/cosmos_cli.py
reco_utils/dataset/covid_utils.py
reco_utils/dataset/criteo.py
reco_utils/dataset/download_utils.py
reco_utils/dataset/mind.py
reco_utils/dataset/movielens.py
reco_utils/dataset/pandas_df_utils.py
reco_utils/dataset/python_splitters.py
reco_utils/dataset/spark_splitters.py
reco_utils/dataset/sparse.py
reco_utils/dataset/split_utils.py
reco_utils/dataset/wikidata.py
reco_utils/evaluation/__init__.py
reco_utils/evaluation/python_evaluation.py
reco_utils/evaluation/spark_evaluation.py
reco_utils/recommender/__init__.py
reco_utils/recommender/cornac/__init__.py
reco_utils/recommender/cornac/cornac_utils.py
reco_utils/recommender/deeprec/__init__.py
reco_utils/recommender/deeprec/deeprec_utils.py
reco_utils/recommender/deeprec/io/__init__.py
reco_utils/recommender/deeprec/io/dkn_item2item_iterator.py
reco_utils/recommender/deeprec/io/dkn_iterator.py
reco_utils/recommender/deeprec/io/iterator.py
reco_utils/recommender/deeprec/io/nextitnet_iterator.py
reco_utils/recommender/deeprec/io/sequential_iterator.py
reco_utils/recommender/deeprec/models/__init__.py
reco_utils/recommender/deeprec/models/base_model.py
reco_utils/recommender/deeprec/models/dkn.py
reco_utils/recommender/deeprec/models/dkn_item2item.py
reco_utils/recommender/deeprec/models/xDeepFM.py
recommender_utils-2021.2.post1623854186.dist-info/AUTHORS.md
recommender_utils-2021.2.post1623854186.dist-info/LICENSE
recommender_utils-2021.2.post1623854186.dist-info/METADATA
recommender_utils-2021.2.post1623854186.dist-info/WHEEL
recommender_utils-2021.2.post1623854186.dist-info/top_level.txt
recommender_utils-2021.2.post1623854186.dist-info/RECORD
