Metadata-Version: 2.1
Name: recommender-utils
Version: 2021.2.post1623854186
Summary: Recommender System Utilities
Home-page: https://github.com/microsoft/recommenders
Author: RecoDev Team at Microsoft
Author-email: RecoDevTeam@service.microsoft.com
License: UNKNOWN
Keywords: recommendations recommenders recommender system engine machine learning python spark gpu
Platform: UNKNOWN
Classifier: Development Status :: 4 - Beta
Classifier: Intended Audience :: Developers
Classifier: Intended Audience :: Science/Research
Classifier: Topic :: Scientific/Engineering
Classifier: Topic :: Software Development :: Libraries :: Python Modules
Classifier: License :: OSI Approved :: MIT License
Classifier: Programming Language :: Python :: 3.6
Requires-Python: >=3.6, <4
